odoo/addons/l10n_th_tax_address/README.rst
odoo/addons/l10n_th_tax_address/__init__.py
odoo/addons/l10n_th_tax_address/__manifest__.py
odoo/addons/l10n_th_tax_address/data/ir_config_parameter.xml
odoo/addons/l10n_th_tax_address/i18n/l10n_th_tax_address.pot
odoo/addons/l10n_th_tax_address/models/__init__.py
odoo/addons/l10n_th_tax_address/models/res_partner.py
odoo/addons/l10n_th_tax_address/readme/CONTRIBUTORS.rst
odoo/addons/l10n_th_tax_address/readme/DESCRIPTION.rst
odoo/addons/l10n_th_tax_address/readme/USAGE.rst
odoo/addons/l10n_th_tax_address/static/description/icon.png
odoo/addons/l10n_th_tax_address/static/description/index.html
odoo/addons/l10n_th_tax_address/tests/__init__.py
odoo/addons/l10n_th_tax_address/tests/test_l10n_th_tax_address.py
odoo/addons/l10n_th_tax_address/views/res_partner_view.xml
odoo_addon_l10n_th_tax_address-16.0.1.1.1.dist-info/METADATA
odoo_addon_l10n_th_tax_address-16.0.1.1.1.dist-info/WHEEL
odoo_addon_l10n_th_tax_address-16.0.1.1.1.dist-info/top_level.txt
odoo_addon_l10n_th_tax_address-16.0.1.1.1.dist-info/RECORD
